kraken.py
kraken_virus-0.1.0.dist-info/licenses/LICENSE
kraken_virus-0.1.0.dist-info/METADATA
kraken_virus-0.1.0.dist-info/WHEEL
kraken_virus-0.1.0.dist-info/top_level.txt
kraken_virus-0.1.0.dist-info/RECORD
