Metadata-Version: 2.4
Name: kraken-virus
Version: 0.1.0
Summary: A virus package for max destruction
Author-email: bluecode <bluecodeyt12@gmail.com>
License: MIT License
Project-URL: Homepage, https://github.com/bluecodeyt12-maker/Kraken-Virus
Project-URL: Repository, https://github.com/bluecodeyt12-maker/Kraken-Virus
Project-URL: Issues, https://github.com/bluecodeyt12-maker/Kraken-Virus/issues
Keywords: kraken,virus,security
Classifier: License :: OSI Approved :: MIT License
Classifier: Programming Language :: Python :: 3
Classifier: Programming Language :: Python :: 3.8
Classifier: Programming Language :: Python :: 3.9
Classifier: Programming Language :: Python :: 3.10
Classifier: Programming Language :: Python :: 3.11
Classifier: Programming Language :: Python :: 3.12
License-File: LICENSE
Dynamic: license-file
